tests/__init__.py
tests/api_test.py
tests/client_test.py
tests/creds.py
tests/extractor_test.py
vkapi8/__init__.py
vkapi8/accesstoken.py
vkapi8/exceptions.py
vkapi8/utils.py
vkapi8/vkapi8.py
vkapi8/vkscripts.py
vkapi8-2.0.1.dist-info/METADATA
vkapi8-2.0.1.dist-info/RECORD
vkapi8-2.0.1.dist-info/WHEEL
vkapi8-2.0.1.dist-info/top_level.txt
