Metadata-Version: 2.1
Name: vkapi8
Version: 2.0.1
Summary: Optimized vk api lib
Home-page: http://github.com/ChickenLover/vkapi8
Author: ChickenLover
Author-email: romangg81@gmail.com
License: UNKNOWN
Platform: UNKNOWN
Requires-Dist: requests
